autogmm/__init__.py
autogmm/_legacy_autogmm.py
autogmm/_legacy_init.py
autogmm/autogmm.py
autogmm-0.1.0.dist-info/licenses/LICENSE
autogmm-0.1.0.dist-info/METADATA
autogmm-0.1.0.dist-info/WHEEL
autogmm-0.1.0.dist-info/top_level.txt
autogmm-0.1.0.dist-info/RECORD
