Metadata-Version: 2.4
Name: autogmm
Version: 0.1.0
Summary: Automatic Gaussian Mixture Modeling in Python
Author: Tingshan Liu
License: BSD 3-Clause License
Project-URL: Homepage, https://github.com/neurodata/autogmm
Project-URL: Repository, https://github.com/neurodata/autogmm
Project-URL: Issues, https://github.com/neurodata/autogmm/issues
Keywords: clustering,gmm,mixture,model selection
Requires-Python: >=3.9
License-File: LICENSE
Requires-Dist: numpy>=1.21
Requires-Dist: scipy>=1.8
Requires-Dist: scikit-learn>=1.1
Requires-Dist: joblib>=1.1
Provides-Extra: dev
Requires-Dist: pytest>=7; extra == "dev"
Requires-Dist: pytest-cov>=4; extra == "dev"
Requires-Dist: ruff>=0.6; extra == "dev"
Requires-Dist: black>=24.4; extra == "dev"
Requires-Dist: pre-commit>=3.6; extra == "dev"
Provides-Extra: docs
Requires-Dist: sphinx>=8; extra == "docs"
Requires-Dist: numpydoc>=1.6; extra == "docs"
Requires-Dist: sphinx-rtd-theme>=2.0; extra == "docs"
Provides-Extra: experiments
Requires-Dist: matplotlib; extra == "experiments"
Requires-Dist: pandas; extra == "experiments"
Requires-Dist: graspologic; extra == "experiments"
Requires-Dist: seaborn; extra == "experiments"
Requires-Dist: tqdm; extra == "experiments"
Requires-Dist: scipy; extra == "experiments"
Requires-Dist: joblib; extra == "experiments"
Requires-Dist: nbformat; extra == "experiments"
Requires-Dist: nbconvert; extra == "experiments"
Requires-Dist: ipykernel; extra == "experiments"
Dynamic: license-file
